pyciede2000/__init__.py
pyciede2000/ciede2000.py
pyciede2000-0.0.21.dist-info/LICENSE
pyciede2000-0.0.21.dist-info/METADATA
pyciede2000-0.0.21.dist-info/WHEEL
pyciede2000-0.0.21.dist-info/top_level.txt
pyciede2000-0.0.21.dist-info/RECORD
