Metadata-Version: 2.1
Name: pyciede2000
Version: 0.0.21
Summary: Python package for calculating CIEDE2000 colour difference.
Home-page: https://github.com/shameempk/pyciede2000
Author: shameempk
Author-email: shameempk@pm.me
License: UNKNOWN
Project-URL: Bug Tracker, https://github.com/shameempk/pyciede2000
Platform: UNKNOWN
Classifier: Programming Language :: Python :: 3
Classifier: License :: OSI Approved :: MIT License
Classifier: Operating System :: OS Independent
Requires-Python: >=3.6
